ipd/__init__.py
ipd/builder.py
ipd/logging.py
ipd/repository.py
ipd/libvirt/__init__.py
ipd/libvirt/constants.py
ipd/libvirt/endpoints.py
ipd/libvirt/error.py
ipd/libvirt/procedures.py
ipd/libvirt/program.py
ipd/libvirt/protocol.py
ipd/libvirt/remote.py
ipd/libvirt/types.py
ipd/metadata/__init__.py
ipd/metadata/resource.py
ipd/metadata/revproxy.py
ipd/metadata/server.py
ipd/metadata/utils.py
ipd/scripts/__init__.py
ipd/scripts/genproto.py
ipd/scripts/ipd.py
ipd/scripts/metaproxy.py
ipd/test/__init__.py
ipd-0.1.2.data/scripts/gen-libvirt-protocol
ipd-0.1.2.data/scripts/ipd
ipd-0.1.2.data/scripts/ipd-metaproxy
ipd-0.1.2.dist-info/DESCRIPTION.rst
ipd-0.1.2.dist-info/entry_points.txt
ipd-0.1.2.dist-info/METADATA
ipd-0.1.2.dist-info/pydist.json
ipd-0.1.2.dist-info/RECORD
ipd-0.1.2.dist-info/top_level.txt
ipd-0.1.2.dist-info/WHEEL
