Metadata-Version: 2.0
Name: ipd
Version: 0.1.2
Summary: Integrated Project Deployer
Home-page: https://github.com/GaretJax/ipd
Author: Jonathan Stoppani
Author-email: jonathan@stoppani.name
License: MIT
Platform: UNKNOWN
Classifier: Development Status :: 4 - Beta
Classifier: Intended Audience :: Developers
Classifier: License :: OSI Approved :: MIT License
Classifier: Operating System :: OS Independent
Classifier: Programming Language :: Python
Classifier: Topic :: Software Development :: Libraries :: Python Modules
Requires-Dist: GitPython (==0.3.2.RC1)
Requires-Dist: Parsley (==1.2)
Requires-Dist: Twisted (==13.2.0)
Requires-Dist: structlog (==0.4.1)
Requires-Dist: txredis (==2.3)
Requires-Dist: lxml (==3.2.5)
Requires-Dist: gitdb (==0.5.4)
Requires-Dist: async (==0.6.1)
Requires-Dist: smmap (==0.8.2)
Requires-Dist: zope.interface (==4.0.5)
